pretix_computop/__init__.py
pretix_computop/apps.py
pretix_computop/payment.py
pretix_computop/paymentmethods.py
pretix_computop/signals.py
pretix_computop/urls.py
pretix_computop/views.py
pretix_computop/locale/de/LC_MESSAGES/django.mo
pretix_computop/locale/de/LC_MESSAGES/django.po
pretix_computop/locale/de_Informal/.gitkeep
pretix_computop/locale/de_Informal/LC_MESSAGES/django.mo
pretix_computop/locale/de_Informal/LC_MESSAGES/django.po
pretix_computop/static/pretix_computop/.gitkeep
pretix_computop/static/pretix_computop/logo.svg
pretix_computop/templates/pretix_computop/.gitkeep
pretix_computop/templates/pretix_computop/checkout_payment_confirm.html
pretix_computop/templates/pretix_computop/checkout_payment_form.html
pretix_computop/templates/pretix_computop/control.html
pretix_computop/templates/pretix_computop/return.html
pretix_firstcash/__init__.py
pretix_firstcash/apps.py
pretix_firstcash/payment.py
pretix_firstcash/paymentmethods.py
pretix_firstcash/signals.py
pretix_firstcash/urls.py
pretix_firstcash/static/pretix_firstcash/logo.svg
pretix_computop-1.1.1.dist-info/LICENSE
pretix_computop-1.1.1.dist-info/METADATA
pretix_computop-1.1.1.dist-info/WHEEL
pretix_computop-1.1.1.dist-info/entry_points.txt
pretix_computop-1.1.1.dist-info/top_level.txt
pretix_computop-1.1.1.dist-info/RECORD
