Metadata-Version: 2.1
Name: pretix-computop
Version: 1.1.1
Summary: Use Computop based payment providers
Author-email: pretix team <support@pretix.eu>
Maintainer-email: pretix team <support@pretix.eu>
License: 
Project-URL: homepage, https://github.com/pretix/pretix-computop
Keywords: pretix
Requires-Python: >=3.9
License-File: LICENSE
Requires-Dist: pycryptodome
